{
  "project_info": {
    "project_number": "667281821952",
    "firebase_url": "https://fir-storegadeneme1-default-rtdb.firebaseio.com",
    "project_id": "fir-storegadeneme1",
    "storage_bucket": "fir-storegadeneme1.appspot.com"
  },
  "client": [
    {
      "client_info": {
        "mobilesdk_app_id": "1:667281821952:android:33315321c043ade4d1a3e5",
        "android_client_info": {
          "package_name": "com.example.firebasedownload"
        }
      },
      "oauth_client": [
        {
          "client_id": "667281821952-mkl3r1mr9i283vasv7v8r6r6uler5o8d.apps.googleusercontent.com",
          "client_type": 3
        }
      ],
      "api_key": [
        {
          "current_key": "AIzaSyDtgaEIcVGsqCTOVrfXqKNQZOUkgz-BU5Y"
        }
      ],
      "services": {
        "appinvite_service": {
          "other_platform_oauth_client": [
            {
              "client_id": "667281821952-mkl3r1mr9i283vasv7v8r6r6uler5o8d.apps.googleusercontent.com",
              "client_type": 3
            }
          ]
        }
      }
    },
    {
      "client_info": {
        "mobilesdk_app_id": "1:667281821952:android:0fd629554133197cd1a3e5",
        "android_client_info": {
          "package_name": "com.example.firebasestorega"
        }
      },
      "oauth_client": [
        {
          "client_id": "667281821952-mkl3r1mr9i283vasv7v8r6r6uler5o8d.apps.googleusercontent.com",
          "client_type": 3
        }
      ],
      "api_key": [
        {
          "current_key": "AIzaSyDtgaEIcVGsqCTOVrfXqKNQZOUkgz-BU5Y"
        }
      ],
      "services": {
        "appinvite_service": {
          "other_platform_oauth_client": [
            {
              "client_id": "667281821952-mkl3r1mr9i283vasv7v8r6r6uler5o8d.apps.googleusercontent.com",
              "client_type": 3
            }
          ]
        }
      }
    },
    {
      "client_info": {
        "mobilesdk_app_id": "1:667281821952:android:e193b153e1c8a5bad1a3e5",
        "android_client_info": {
          "package_name": "com.example.reklam"
        }
      },
      "oauth_client": [
        {
          "client_id": "667281821952-mkl3r1mr9i283vasv7v8r6r6uler5o8d.apps.googleusercontent.com",
          "client_type": 3
        }
      ],
      "api_key": [
        {
          "current_key": "AIzaSyDtgaEIcVGsqCTOVrfXqKNQZOUkgz-BU5Y"
        }
      ],
      "services": {
        "appinvite_service": {
          "other_platform_oauth_client": [
            {
              "client_id": "667281821952-mkl3r1mr9i283vasv7v8r6r6uler5o8d.apps.googleusercontent.com",
              "client_type": 3
            }
          ]
        }
      }
    },
    {
      "client_info": {
        "mobilesdk_app_id": "1:667281821952:android:23661e7139fb39f1d1a3e5",
        "android_client_info": {
          "package_name": "com.example.reklamdeneme1"
        }
      },
      "oauth_client": [
        {
          "client_id": "667281821952-mkl3r1mr9i283vasv7v8r6r6uler5o8d.apps.googleusercontent.com",
          "client_type": 3
        }
      ],
      "api_key": [
        {
          "current_key": "AIzaSyDtgaEIcVGsqCTOVrfXqKNQZOUkgz-BU5Y"
        }
      ],
      "services": {
        "appinvite_service": {
          "other_platform_oauth_client": [
            {
              "client_id": "667281821952-mkl3r1mr9i283vasv7v8r6r6uler5o8d.apps.googleusercontent.com",
              "client_type": 3
            }
          ]
        }
      }
    },
    {
      "client_info": {
        "mobilesdk_app_id": "1:667281821952:android:14e05c4620673df5d1a3e5",
        "android_client_info": {
          "package_name": "com.example.videokontrol"
        }
      },
      "oauth_client": [
        {
          "client_id": "667281821952-mkl3r1mr9i283vasv7v8r6r6uler5o8d.apps.googleusercontent.com",
          "client_type": 3
        }
      ],
      "api_key": [
        {
          "current_key": "AIzaSyDtgaEIcVGsqCTOVrfXqKNQZOUkgz-BU5Y"
        }
      ],
      "services": {
        "appinvite_service": {
          "other_platform_oauth_client": [
            {
              "client_id": "667281821952-mkl3r1mr9i283vasv7v8r6r6uler5o8d.apps.googleusercontent.com",
              "client_type": 3
            }
          ]
        }
      }
    },
    {
      "client_info": {
        "mobilesdk_app_id": "1:667281821952:android:bb460039244190afd1a3e5",
        "android_client_info": {
          "package_name": "com.example.videoview"
        }
      },
      "oauth_client": [
        {
          "client_id": "667281821952-mkl3r1mr9i283vasv7v8r6r6uler5o8d.apps.googleusercontent.com",
          "client_type": 3
        }
      ],
      "api_key": [
        {
          "current_key": "AIzaSyDtgaEIcVGsqCTOVrfXqKNQZOUkgz-BU5Y"
        }
      ],
      "services": {
        "appinvite_service": {
          "other_platform_oauth_client": [
            {
              "client_id": "667281821952-mkl3r1mr9i283vasv7v8r6r6uler5o8d.apps.googleusercontent.com",
              "client_type": 3
            }
          ]
        }
      }
    }
  ],
  "configuration_version": "1"
}